extractor_api_lib/api_endpoints/__init__.py
extractor_api_lib/api_endpoints/file_extractor.py
extractor_api_lib/api_endpoints/source_extractor.py
extractor_api_lib/apis/__init__.py
extractor_api_lib/apis/extractor_api.py
extractor_api_lib/apis/extractor_api_base.py
extractor_api_lib/dependency_container.py
extractor_api_lib/extractors/__init__.py
extractor_api_lib/extractors/information_extractor.py
extractor_api_lib/extractors/information_file_extractor.py
extractor_api_lib/file_services/file_service.py
extractor_api_lib/impl/__init__.py
extractor_api_lib/impl/api_endpoints/__init__.py
extractor_api_lib/impl/api_endpoints/general_file_extractor.py
extractor_api_lib/impl/api_endpoints/general_source_extractor.py
extractor_api_lib/impl/extractor_api_impl.py
extractor_api_lib/impl/extractors/__init__.py
extractor_api_lib/impl/extractors/confluence_extractor.py
extractor_api_lib/impl/extractors/file_extractors/__init__.py
extractor_api_lib/impl/extractors/file_extractors/docling_extractor.py
extractor_api_lib/impl/extractors/file_extractors/epub_extractor.py
extractor_api_lib/impl/extractors/file_extractors/image_extractor.py
extractor_api_lib/impl/extractors/file_extractors/markitdown_extractor.py
extractor_api_lib/impl/extractors/file_extractors/ms_docs_extractor.py
extractor_api_lib/impl/extractors/file_extractors/pdf_extractor.py
extractor_api_lib/impl/extractors/file_extractors/xml_extractor.py
extractor_api_lib/impl/extractors/sitemap_extractor.py
extractor_api_lib/impl/file_services/__init__.py
extractor_api_lib/impl/file_services/s3_service.py
extractor_api_lib/impl/mapper/__init__.py
extractor_api_lib/impl/mapper/confluence_langchain_document2information_piece.py
extractor_api_lib/impl/mapper/internal2external_information_piece.py
extractor_api_lib/impl/mapper/langchain_document2information_piece.py
extractor_api_lib/impl/mapper/sitemap_document2information_piece.py
extractor_api_lib/impl/settings/__init__.py
extractor_api_lib/impl/settings/s3_settings.py
extractor_api_lib-3.4.0.dist-info/METADATA
extractor_api_lib-3.4.0.dist-info/WHEEL
extractor_api_lib-3.4.0.dist-info/RECORD
